tealish/__init__.py
tealish/base.py
tealish/build.py
tealish/cli.py
tealish/errors.py
tealish/expression_nodes.py
tealish/langspec.json
tealish/langspec.py
tealish/nodes.py
tealish/opdocs.py
tealish/rewrite.py
tealish/scope.py
tealish/tealish_builtins.py
tealish/tealish_expressions.tx
tealish/tree.py
tealish/tx_expressions.py
tealish/utils.py
tealish/write_html.py
tealish-0.0.2.dist-info/LICENSE
tealish-0.0.2.dist-info/METADATA
tealish-0.0.2.dist-info/WHEEL
tealish-0.0.2.dist-info/entry_points.txt
tealish-0.0.2.dist-info/top_level.txt
tealish-0.0.2.dist-info/RECORD
