Metadata-Version: 2.1
Name: tealish
Version: 0.0.2
Summary: The Tealish language for the Algorand Virtual Machine.
Author-email: Tinyman <hello@tinyman.org>
Project-URL: Homepage, https://github.com/Hipo/tealish
Project-URL: Bug Tracker, https://github.com/Hipo/tealish/issues
Classifier: Programming Language :: Python :: 3
Classifier: License :: OSI Approved :: MIT License
Classifier: Operating System :: OS Independent
Requires-Python: >=3.8
License-File: LICENSE
Requires-Dist: textX (>=3.0.0)
Requires-Dist: click (>=8.1.3)
Requires-Dist: requests (>=2.0.0)
Requires-Dist: py-algorand-sdk (>=1.20.0)
